stlconverter/__init__.py
stlconverter/__main__.py
stlconverter/modules/__init__.py
stlconverter/modules/conversion.py
stlconverter/modules/input_handling.py
stlconverter-1.0.2.dist-info/LICENSE
stlconverter-1.0.2.dist-info/METADATA
stlconverter-1.0.2.dist-info/WHEEL
stlconverter-1.0.2.dist-info/top_level.txt
stlconverter-1.0.2.dist-info/RECORD
